Logic_test/mux_2to1.v
module mux_2to1 (s,d0,d1,y);
output y;
input d0;
input d1;
input s;

assign y = ~s&d0 | s&d1 ; 

    
endmodule

Logic_test/mux_2to1_tb.v
module mux_2to1_tb;
reg d0;
reg d1;
reg s;
wire y;


mux_2to1 utt(s,d0,d1,y);

initial begin
// ---- สั่งบันทึกสัญญาณลงไฟล์ .vcd สำหรับ GTKWave ----
$dumpfile("mux_2to1.vcd");
$dumpvars(0, mux_2to1_tb);
// ---- ส่วนหัวของตารางผลลัพธ์ ----
$display("=== Hello World from Icarus Verilog : mux_2to1 ===");
        $display(" time(ns)   s         d0      d1 |  y ");
        
        // แก้ไข %s เป็น %b ทั้งหมด
        $monitor("     %4d   %b         %b      %b |  %b ", $time, s,d0,d1,y);
        
        // ---- ป้อนค่าสัญญาณทดสอบ ----
        s = 1'b0; d0 = 1'b0; d1 = 1'b0;
        #5 s = 1'b0; d0 = 1'b1; d1 = 1'b0;
        #5 s = 1'b0; d0 = 1'b0; d1 = 1'b1;
        #5 s = 1'b0; d0 = 1'b1; d1 = 1'b1;
        
        #5 s = 1'b1; d0 = 1'b0; d1 = 1'b0;
        #5 s = 1'b1; d0 = 1'b1; d1 = 1'b0;
        #5 s = 1'b1; d0 = 1'b0; d1 = 1'b1;
        #5 s = 1'b1; d0 = 1'b1; d1 = 1'b1;
        
        // หน่วงเวลาอีก 5 ก่อนจบ เพื่อให้ดูกราฟจังหวะสุดท้ายได้ชัดเจน
        #5;
        
        $display("=== Simulation finished ===");
        $finish;
end


endmodule

Logic_test/mux_2to1.vcd
$date
	Thu Sep 17 13:51:13 2026
$end
$version
	Icarus Verilog
$end
$timescale
	1s
$end
$scope module mux_2to1_tb $end
$var wire 1 ! y $end
$var reg 1 " d0 $end
$var reg 1 # d1 $end
$var reg 1 $ s $end
$scope module utt $end
$var wire 1 " d0 $end
$var wire 1 # d1 $end
$var wire 1 $ s $end
$var wire 1 ! y $end
$upscope $end
$upscope $end
$enddefinitions $end
$comment Show the parameter values. $end
$dumpall
$end
#0
$dumpvars
0$
0#
0"
0!
$end
#5
1!
1"
#10
0!
1#
0"
#15
1!
1"
#20
0!
0#
0"
1$
#25
1"
#30
1!
1#
0"
#35
1"
