Logic_test/SRLatch.v
module SRLatch (R,S,Q,QN);
input R;
input S;
output Q;
output QN;

nor nor_1(Q,R,QN);
nor nor_2(QN,S,Q);
    
endmodule

Logic_test/SRLatch_tb.v
module SRLatchStimulus;
reg R;
reg S;
wire Q;
wire QN;


SRLatch utt(R,S,Q,QN);

initial begin
// ---- สั่งบันทึกสัญญาณลงไฟล์ .vcd สำหรับ GTKWave ----
$dumpfile("SRLatch.vcd");
$dumpvars(0, SRLatchStimulus);
// ---- ส่วนหัวของตารางผลลัพธ์ ----
$display("=== Hello World from Icarus Verilog : SRLatch ===");
        $display(" time(ns)   R S  |  Q QN ");
        
        // แก้ไข %s เป็น %b ทั้งหมด
        $monitor("     %4d   %b  %b |  %b  %b ", $time, R,S,Q,QN);

        S=0; R=0;  
        #5 S=1; R=0; 
        #5 S=0; R=0; 
        #5 S=0; R=1; 
        #5 S=0; R=0; 
        #5 S=1; R=0;
        #5 S=0; R=1; 
        #5 S=1; R=1; 
        #5 S=0; R=0; 
        #5 

        $display("=== Simulation finished ===");
        $finish;
end


endmodule

Logic_test/SRLatch.vcd
$date
	Thu Sep 17 13:53:27 2026
$end
$version
	Icarus Verilog
$end
$timescale
	1s
$end
$scope module SRLatchStimulus $end
$var wire 1 ! QN $end
$var wire 1 " Q $end
$var reg 1 # R $end
$var reg 1 $ S $end
$scope module utt $end
$var wire 1 " Q $end
$var wire 1 ! QN $end
$var wire 1 # R $end
$var wire 1 $ S $end
$upscope $end
$upscope $end
$enddefinitions $end
$comment Show the parameter values. $end
$dumpall
$end
#0
$dumpvars
0$
0#
x"
x!
$end
#5
1"
0!
1$
#10
0$
#15
1!
0"
1#
#20
0#
#25
1"
0!
1$
#30
1!
0"
1#
0$
#35
0!
1$
#40
1!
0#
0$
